{
  "syntax": {
    "paths": [],
    "exclude": [
      "tests",
      "vendor",
      "node_modules",
      ".git",
      ".idea",
      ".vscode",
      "coverage",
      ".phpunit.cache",
      ".psalm-cache",
      "build",
      "dist",
      "tmp",
      ".tmp",
      "storage",
      "bootstrap/cache",
      "var/cache"
    ]
  },
  "duplicates": {
    "paths": [],
    "exclude": [
      "tests",
      "vendor",
      "node_modules",
      ".git",
      ".idea",
      ".vscode",
      "coverage",
      ".phpunit.cache",
      ".psalm-cache",
      "build",
      "dist",
      "tmp",
      ".tmp",
      "storage",
      "bootstrap/cache",
      "var/cache",
      "storage/framework/views"
    ],
    "mode": "audit",
    "normalize": true,
    "fuzzy": true,
    "near_miss": true,
    "min_lines": 4,
    "min_tokens": 70,
    "min_statements": 3,
    "min_similarity": 0.8,
    "baseline": "",
    "write_baseline": "",
    "json": false
  },
  "api": {
    "paths": [],
    "exclude": [
      "tests",
      "vendor",
      "node_modules",
      ".git",
      ".idea",
      ".vscode",
      "coverage",
      ".phpunit.cache",
      ".psalm-cache",
      "build",
      "dist",
      "tmp",
      ".tmp",
      "storage",
      "bootstrap/cache",
      "var/cache"
    ],
    "include_protected": true,
    "baseline": "",
    "write_baseline": "",
    "json": false
  }
}
